regml_core/__init__.py
regml_core/lib/__init__.py
regml_core/lib/interfaces/__init__.py
regml_core/lib/interfaces/run_task_thunk.py
regml_core/lib/regml.py
regml_core/lib/regml_core__hello_world.py
regml_core/lib/remote_host/__init__.py
regml_core/lib/remote_host/http_remote_connector.py
regml_core/lib/remote_host/remote_connector.py
regml_core/lib/remote_host/remote_host.py
regml_core/lib/remote_host/remote_host_error.py
regml_core/tests/__init__.py
regml_core/tests/test_get_spec.py
regml_core/tests/test_regml_run_task.py
regml_core/tests/test_remote_host_run_task.py
regml_core/vendor/__init__.py
regml_core/vendor/openai/__init__.py
regml_core/vendor/openai/openai-chat.py
regml_core-0.0.2.dist-info/METADATA
regml_core-0.0.2.dist-info/WHEEL
regml_core-0.0.2.dist-info/RECORD
