Metadata-Version: 2.1
Name: regml_core
Version: 0.0.2
Summary: Regscale ML Library
Author: Luke Bechtel
Author-email: lbechtel@regscale.com
Requires-Python: >=3.8
Classifier: Programming Language :: Python :: 3
Classifier: Programming Language :: Python :: 3.8
Classifier: Programming Language :: Python :: 3.9
Classifier: Programming Language :: Python :: 3.10
Classifier: Programming Language :: Python :: 3.11
Classifier: Programming Language :: Python :: 3.12
Requires-Dist: aiohttp (>=3.9.3,<4.0.0)
Requires-Dist: inflection (>=0.5.1,<0.6.0)
Requires-Dist: numpy (>=1.2.3,<2.0.0)
